stuffer/__init__.py
stuffer/apt.py
stuffer/configuration.py
stuffer/content.py
stuffer/core.py
stuffer/debconf.py
stuffer/docker.py
stuffer/files.py
stuffer/main.py
stuffer/pip.py
stuffer/store.py
stuffer/system.py
stuffer/user.py
stuffer/utils.py
stuffer/contrib/__init__.py
stuffer/contrib/adobe.py
stuffer/contrib/docker.py
stuffer/contrib/dropbox.py
stuffer/contrib/google.py
stuffer/contrib/hashicorp.py
stuffer/contrib/jetbrains.py
stuffer/contrib/kafka.py
stuffer/contrib/nettools.py
stuffer/contrib/spotify.py
stuffer-0.0.10.dist-info/DESCRIPTION.rst
stuffer-0.0.10.dist-info/METADATA
stuffer-0.0.10.dist-info/RECORD
stuffer-0.0.10.dist-info/WHEEL
stuffer-0.0.10.dist-info/entry_points.txt
stuffer-0.0.10.dist-info/metadata.json
stuffer-0.0.10.dist-info/top_level.txt
