Metadata-Version: 2.0
Name: stuffer
Version: 0.0.10
Summary: Simplified, container-friendly provisioning
Home-page: http://bitbucket.org/mapflat/stuffer
Maintainer: Lars Albertsson
Maintainer-email: lalle@mapflat.com
License: UNKNOWN
Platform: UNKNOWN
Requires-Dist: click
